{
    "type": "FeatureCollection",
    "name": "SWDC_Urban_2024_2025 - Imagery_Centres",
    "crs": {
        "type": "name",
        "properties": {
            "name": "urn:ogc:def:crs:OGC:1.3:CRS84"
        }
    },
    "xy_coordinate_resolution": 1e-15,
    "features": [
        {
            "type": "Feature",
            "properties": {
                "Project": "PGRM3032",
                "Company_Name": "Tasman DC",
                "SN_No": "SN14247",
                "Description": "Tasman Riverbed - 2022 1320 m AMGL Flying & orthos",
                "OrthoGSD_m": 0.075,
                "PointDensity_(points/m2)": null,
                "Area": 65.909316600125536,
                "Percentage_Coverage": 100.0
            },
            "geometry": {
                "type": "Point",
                "coordinates": [
                    175.414161707068388,
                    -41.169890632462248
                ]
            }
        }
    ]
}